Metadata-Version: 1.1
Name: django-simditor
Version: 0.0.15
Summary: Django admin Simditor integration.
Home-page: https://github.com/istommao/django-simditor
Author: Silence
Author-email: istommao@gmail.com
License: UNKNOWN
Keywords: Django admin Simditor integration!
Platform: UNKNOWN
Classifier: Programming Language :: Python
Classifier: Programming Language :: Python :: 2.7
Classifier: Programming Language :: Python :: 3.3
Classifier: Programming Language :: Python :: 3.4
Classifier: Programming Language :: Python :: 3.5
Classifier: License :: OSI Approved :: MIT License
Classifier: Operating System :: OS Independent
Classifier: Framework :: Django
Classifier: Intended Audience :: Developers
Classifier: Topic :: Internet :: WWW/HTTP :: Dynamic Content
